avalon/__init__.py
avalon/__main__.py
avalon/__version__.py
avalon/api.py
avalon/inventory.py
avalon/io.py
avalon/lib.py
avalon/mock.py
avalon/pipeline.py
avalon/schema.py
avalon/version.py
avalon/fusion/__init__.py
avalon/fusion/lib.py
avalon/fusion/pipeline.py
avalon/fusion/workio.py
avalon/houdini/__init__.py
avalon/houdini/lib.py
avalon/houdini/pipeline.py
avalon/houdini/workio.py
avalon/maya/__init__.py
avalon/maya/commands.py
avalon/maya/compat.py
avalon/maya/interactive.py
avalon/maya/lib.py
avalon/maya/pipeline.py
avalon/maya/util.py
avalon/maya/workio.py
avalon/nuke/__init__.py
avalon/nuke/command.py
avalon/nuke/lib.py
avalon/nuke/pipeline.py
avalon/nuke/workio.py
avalon/schema/application-1.0.json
avalon/schema/asset-1.0.json
avalon/schema/asset-2.0.json
avalon/schema/config-1.0.json
avalon/schema/container-1.0.json
avalon/schema/container-2.0.json
avalon/schema/inventory-1.0.json
avalon/schema/project-2.0.json
avalon/schema/representation-1.0.json
avalon/schema/representation-2.0.json
avalon/schema/session-1.0.json
avalon/schema/shaders-1.0.json
avalon/schema/subset-1.0.json
avalon/schema/subset-2.0.json
avalon/schema/subset-3.0.json
avalon/schema/version-1.0.json
avalon/schema/version-2.0.json
avalon/schema/version-3.0.json
avalon/shell/__init__.py
avalon/style/__init__.py
avalon/style/colors.py
avalon/style/compile_qrc.py
avalon/style/pyqt5_style_rc.py
avalon/style/pyqt_style_rc.py
avalon/style/pyside_style_rc.py
avalon/style/style.qrc
avalon/style/style.qss
avalon/style/rc/Hmovetoolbar.png
avalon/style/rc/Hsepartoolbar.png
avalon/style/rc/Vmovetoolbar.png
avalon/style/rc/Vsepartoolbar.png
avalon/style/rc/branch_closed-on.png
avalon/style/rc/branch_closed.png
avalon/style/rc/branch_open-on.png
avalon/style/rc/branch_open.png
avalon/style/rc/checkbox_checked.png
avalon/style/rc/checkbox_checked_disabled.png
avalon/style/rc/checkbox_checked_focus.png
avalon/style/rc/checkbox_indeterminate.png
avalon/style/rc/checkbox_indeterminate_disabled.png
avalon_core-5.7.15.dist-info/LICENSE
avalon_core-5.7.15.dist-info/METADATA
avalon_core-5.7.15.dist-info/WHEEL
avalon_core-5.7.15.dist-info/top_level.txt
avalon_core-5.7.15.dist-info/RECORD
